audio_processor/__init__.py
audio_processor/silence_remover.py
audio_processor_GovGPT-0.1.0.dist-info/LICENSE
audio_processor_GovGPT-0.1.0.dist-info/METADATA
audio_processor_GovGPT-0.1.0.dist-info/WHEEL
audio_processor_GovGPT-0.1.0.dist-info/top_level.txt
audio_processor_GovGPT-0.1.0.dist-info/RECORD
